telq/.DS_Store
telq/__init__.py
telq/authentication/__init__.py
telq/endpoints/__init__.py
telq/networks/__init__.py
telq/session/__init__.py
telq/session/session_data.py
telq/supplier/__init__.py
telq/supplier/supplier_data.py
telq/tests/__init__.py
telq/tests/lnt.py
telq/tests/model.py
telq/tests/mt.py
telq/util/rest.py
telq/util/version.py
telq-1.3.5.dist-info/LICENSE
telq-1.3.5.dist-info/METADATA
telq-1.3.5.dist-info/WHEEL
telq-1.3.5.dist-info/RECORD
